mcp_web_search/main.py
mcp_web_search/rag.py
mcp_web_search/search.py
mcp_web_search-0.1.0.dist-info/METADATA
mcp_web_search-0.1.0.dist-info/WHEEL
mcp_web_search-0.1.0.dist-info/entry_points.txt
mcp_web_search-0.1.0.dist-info/licenses/LICENSE
mcp_web_search-0.1.0.dist-info/RECORD
